pyecom/__init__.py
pyecom/main.py
pyecom-0.1.1.dist-info/LICENSE
pyecom-0.1.1.dist-info/METADATA
pyecom-0.1.1.dist-info/WHEEL
pyecom-0.1.1.dist-info/top_level.txt
pyecom-0.1.1.dist-info/RECORD
