Metadata-Version: 2.1
Name: pyecom
Version: 0.1.1
Summary: ecommerce api
Home-page: https://github.com/xavibj/pyecom
Author: Xavi Bolivar
Author-email: xavi@xavi.net
License: UNKNOWN
Project-URL: Documentation, https://github.com/xavibj/pyecom
Project-URL: Bug Reports, https://github.com/xavibj/pyecom/issues
Project-URL: Source Code, https://github.com/xavibj/pyecom
Keywords: ecommerce,api
Platform: UNKNOWN
Classifier: Development Status :: 1 - Planning
Classifier: Intended Audience :: Developers
Classifier: Topic :: Internet
Classifier: Programming Language :: Python :: 3
Classifier: Programming Language :: Python :: 3.6
Classifier: Programming Language :: Python :: 3.7
Classifier: Programming Language :: Python :: 3.8
Classifier: Programming Language :: Python :: 3.9
Classifier: Programming Language :: Python :: 3 :: Only
Classifier: License :: OSI Approved :: MIT License
Classifier: Operating System :: OS Independent
Requires-Python: >=3.6
Provides-Extra: dev
Requires-Dist: check-manifest ; extra == 'dev'
